simpa/__init__.py
simpa/core/__init__.py
simpa/core/pipeline_element_base.py
simpa/core/simulation.py
simpa/core/device_digital_twins/__init__.py
simpa/core/device_digital_twins/digital_device_twin_base.py
simpa/core/device_digital_twins/detection_geometries/__init__.py
simpa/core/device_digital_twins/detection_geometries/curved_array.py
simpa/core/device_digital_twins/detection_geometries/detection_geometry_base.py
simpa/core/device_digital_twins/detection_geometries/linear_array.py
simpa/core/device_digital_twins/detection_geometries/planar_array.py
simpa/core/device_digital_twins/illumination_geometries/__init__.py
simpa/core/device_digital_twins/illumination_geometries/disk_illumination.py
simpa/core/device_digital_twins/illumination_geometries/gaussian_beam_illumination.py
simpa/core/device_digital_twins/illumination_geometries/illumination_geometry_base.py
simpa/core/device_digital_twins/illumination_geometries/ithera_msot_acuity_illumination.py
simpa/core/device_digital_twins/illumination_geometries/ithera_msot_invision_illumination.py
simpa/core/device_digital_twins/illumination_geometries/pencil_array_illumination.py
simpa/core/device_digital_twins/illumination_geometries/pencil_beam_illumination.py
simpa/core/device_digital_twins/illumination_geometries/rectangle_illumination.py
simpa/core/device_digital_twins/illumination_geometries/ring_illumination.py
simpa/core/device_digital_twins/illumination_geometries/slit_illumination.py
simpa/core/device_digital_twins/pa_devices/__init__.py
simpa/core/device_digital_twins/pa_devices/ithera_msot_acuity.py
simpa/core/device_digital_twins/pa_devices/ithera_msot_invision.py
simpa/core/device_digital_twins/pa_devices/ithera_rsom.py
simpa/core/device_digital_twins/pa_devices/photoacoustic_device.py
simpa/core/processing_components/__init__.py
simpa/core/processing_components/processing_component_base.py
simpa/core/processing_components/monospectral/__init__.py
simpa-1.0.0.dist-info/LICENSE.md
simpa-1.0.0.dist-info/METADATA
simpa-1.0.0.dist-info/WHEEL
simpa-1.0.0.dist-info/top_level.txt
simpa-1.0.0.dist-info/RECORD
