Metadata-Version: 2.1
Name: simpa
Version: 1.0.0
Summary: Simulation and Image Processing for Photonics and Acoustics
Author: Janek Groehl <janekgroehl@live.de>
Author-email: "Division of Intelligent Medical Systems (IMSY), DKFZ" <k.dreher@dkfz-heidelberg.de>
License: MIT
Project-URL: Homepage, https://github.com/IMSY-DKFZ/simpa
Project-URL: Documentation, https://simpa.readthedocs.io/en/main/
Project-URL: Repository, https://github.com/IMSY-DKFZ/simpa
Keywords: simulation,photonics,acoustics
Requires-Python: >=3.9
License-File: LICENSE.md
Requires-Dist: matplotlib >=3.5.0
Requires-Dist: numpy >=1.21.4
Requires-Dist: scipy >=1.13.0
Requires-Dist: pynrrd >=0.4.2
Requires-Dist: scikit-image >=0.18.3
Requires-Dist: xmltodict >=0.12.0
Requires-Dist: h5py >=3.6.0
Requires-Dist: pandas >=1.3.4
Requires-Dist: coverage >=6.1.2
Requires-Dist: Deprecated >=1.2.13
Requires-Dist: torch >=1.10.0
Requires-Dist: python-dotenv >=0.19.2
Requires-Dist: pacfish >=0.4.4
Requires-Dist: requests >=2.26.0
Requires-Dist: wget >=3.2
Requires-Dist: jdata >=0.5.2
Requires-Dist: pre-commit >=3.2.2
Requires-Dist: PyWavelets
Requires-Dist: scikit-learn >=1.1.0
Provides-Extra: docs
Requires-Dist: sphinx-rtd-theme <3.0.0,>=2.0.0 ; extra == 'docs'
Requires-Dist: Sphinx <6.0.0,>=5.1.1 ; extra == 'docs'
Requires-Dist: myst-parser <1.1,>=0.18.0 ; extra == 'docs'
Provides-Extra: profile
Requires-Dist: pytorch-memlab >=0.3.0 ; extra == 'profile'
Requires-Dist: line-profiler >=4.0.0 ; extra == 'profile'
Requires-Dist: memory-profiler >=0.61.0 ; extra == 'profile'
Requires-Dist: tabulate >=0.9.0 ; extra == 'profile'
Provides-Extra: testing
Requires-Dist: mdutils >=1.4.0 ; extra == 'testing'
Requires-Dist: pypandoc >=1.13 ; extra == 'testing'
Requires-Dist: pypandoc-binary >=1.13 ; extra == 'testing'
